pkmb/__init__.py
pkmb/programs.py
pkmb-0.1.2.dist-info/METADATA
pkmb-0.1.2.dist-info/WHEEL
pkmb-0.1.2.dist-info/top_level.txt
pkmb-0.1.2.dist-info/RECORD
