Metadata-Version: 2.4
Name: pkmb
Version: 0.1.2
Summary: A comprehensive NLP and Machine Learning package with example implementations
Home-page: https://github.com/yourusername/pkmb
Author: Your Name
Author-email: your.email@example.com
Keywords: nlp machine-learning deep-learning text-processing vae lstm word-embeddings
Classifier: Development Status :: 3 - Alpha
Classifier: Intended Audience :: Education
Classifier: Intended Audience :: Science/Research
Classifier: License :: OSI Approved :: MIT License
Classifier: Programming Language :: Python :: 3
Classifier: Programming Language :: Python :: 3.8
Classifier: Programming Language :: Python :: 3.9
Classifier: Programming Language :: Python :: 3.10
Classifier: Topic :: Scientific/Engineering :: Artificial Intelligence
Classifier: Topic :: Text Processing :: Linguistic
Requires-Python: >=3.8
Requires-Dist: nltk>=3.8.0
Requires-Dist: pandas>=2.0.0
Requires-Dist: scikit-learn>=1.0.0
Requires-Dist: requests>=2.25.0
Requires-Dist: gensim>=4.0.0
Requires-Dist: scipy==1.11.4
Requires-Dist: tensorflow>=2.12.0
Requires-Dist: matplotlib>=3.5.0
Requires-Dist: numpy>=1.21.0
Requires-Dist: torch>=2.0.0
Requires-Dist: PyMuPDF>=1.22.0
Dynamic: author
Dynamic: author-email
Dynamic: classifier
Dynamic: description
Dynamic: description-content-type
Dynamic: home-page
Dynamic: keywords
Dynamic: requires-dist
Dynamic: requires-python
Dynamic: summary
